aprstastic/__about__.py
aprstastic/__init__.py
aprstastic/__main__.py
aprstastic/_aprs_client.py
aprstastic/_aprs_symbols.py
aprstastic/_config.py
aprstastic/_config_const.py
aprstastic/_gateway.py
aprstastic/_registry.py
aprstastic/res/precompiled_registrations.json
aprstastic-0.0.1a26.dist-info/METADATA
aprstastic-0.0.1a26.dist-info/WHEEL
aprstastic-0.0.1a26.dist-info/licenses/LICENSE
aprstastic-0.0.1a26.dist-info/RECORD
