Metadata-Version: 2.4
Name: aprstastic
Version: 0.0.1a26
Summary: A Meshtastic-APRS Gateway
Project-URL: Documentation, https://github.com/afourney/aprstastic#readme
Project-URL: Issues, https://github.com/afourney/aprstastic/issues
Project-URL: Source, https://github.com/afourney/aprstastic
Author-email: Adam Fourney <adam.fourney@gmail.com>
License-File: LICENSE
Keywords: aprs,aprs-gateway,aprs-is,gateway,lora,lora-gateway,meshtastic,meshtastic-gateway
Classifier: Development Status :: 4 - Beta
Classifier: Programming Language :: Python
Classifier: Programming Language :: Python :: 3.10
Classifier: Programming Language :: Python :: 3.11
Classifier: Programming Language :: Python :: 3.12
Classifier: Programming Language :: Python :: Implementation :: CPython
Classifier: Programming Language :: Python :: Implementation :: PyPy
Classifier: Topic :: Communications :: Ham Radio
Requires-Python: >=3.10
Requires-Dist: aprslib
Requires-Dist: meshtastic
Requires-Dist: packaging
Requires-Dist: requests
